AUTHORS
Changelog
INSTALL
LICENSE
MANIFEST.in
README
THANKS
TODO
setup.py
src/qam/__init__.py
src/qam/amqp_credentials.py
src/qam/qam_proxy.py
src/qam/qam_server.py
src/qam.egg-info/PKG-INFO
src/qam.egg-info/SOURCES.txt
src/qam.egg-info/dependency_links.txt
src/qam.egg-info/requires.txt
src/qam.egg-info/top_level.txt
tests/__init__.py
tests/custom_exception.py
tests/custom_exception.pyc
tests/qamtest.py
tests/qamtest.py~
tests/qamtestserver.py
tests/qamtestserver.pyc
tests/qamtestserver.py~
tests/runtests.sh
tests/log/.hidden
tests/log/qamproxy.log
tests/log/qamproxy.log.1
tests/log/qamserver.log
tests/log/qamserver.log.1
tests/log/qamserver.log.2
tests/log/qamserver.log.3
tests/log/qamserver.log.4
tests/log/qamserver.log.5
tests/log/qamtest.log