Metadata-Version: 1.0
Name: qam
Version: 0.2.14
Summary: QAM is a simple RPC Framework which uses the AMQP Protocol as Transport Protocol.
Home-page: http://packages.python.org/qam
Author: QAM Team
Author-email: qamteam@gmail.com
License: UNKNOWN
Keywords: rpc amqp
Platform: any
Classifier: Development Status :: 3 - Alpha
Classifier: Operating System :: OS Independent
Classifier: Programming Language :: Python
Classifier: License :: OSI Approved :: BSD License
Classifier: Intended Audience :: Developers
Classifier: Topic :: Communications
Classifier: Topic :: System :: Distributed Computing
Classifier: Topic :: Software Development :: Libraries :: Python Modules
